aws_bedrock_a2a_proxy/__init__.py
aws_bedrock_a2a_proxy/a2a_proxy.py
aws_bedrock_a2a_proxy/agentcore_client.py
aws_bedrock_a2a_proxy/agentcore_http_client.py
aws_bedrock_a2a_proxy/main.py
aws_bedrock_a2a_proxy-0.1.2.dist-info/METADATA
aws_bedrock_a2a_proxy-0.1.2.dist-info/WHEEL
aws_bedrock_a2a_proxy-0.1.2.dist-info/RECORD
