Metadata-Version: 2.4
Name: aws-bedrock-a2a-proxy
Version: 0.1.2
Summary: A2A server for AWS Bedrock AgentCore agents
Author: Dave Kerr
Requires-Python: >=3.11
Requires-Dist: a2a-sdk[sqlite]>=0.2.12
Requires-Dist: boto3>=1.34.0
Requires-Dist: click>=8.0.0
Requires-Dist: fastapi>=0.104.0
Requires-Dist: httpx>=0.25.0
Requires-Dist: pydantic>=2.5.0
Requires-Dist: python-dotenv>=1.0.0
Requires-Dist: requests>=2.31.0
Requires-Dist: uvicorn>=0.34.2
Provides-Extra: dev
Requires-Dist: black>=23.0.0; extra == 'dev'
Requires-Dist: flake8>=6.0.0; extra == 'dev'
Requires-Dist: httpx>=0.25.0; extra == 'dev'
Requires-Dist: pyright>=1.1.403; extra == 'dev'
Requires-Dist: pytest-asyncio>=1.1.0; extra == 'dev'
Requires-Dist: pytest-cov>=6.2.1; extra == 'dev'
Requires-Dist: pytest>=8.0.0; extra == 'dev'
